MANIFEST.in
README.rst
pyproject.toml
requirements.txt
setup.cfg
setup.py
ta_bitwarden_cli/__init__.py
ta_bitwarden_cli/download_bitwarden.py
ta_bitwarden_cli/exceptions.py
ta_bitwarden_cli/handler.py
ta_bitwarden_cli/ta_bitwarden_cli.py
ta_bitwarden_cli.egg-info/PKG-INFO
ta_bitwarden_cli.egg-info/SOURCES.txt
ta_bitwarden_cli.egg-info/dependency_links.txt
ta_bitwarden_cli.egg-info/entry_points.txt
ta_bitwarden_cli.egg-info/not-zip-safe
ta_bitwarden_cli.egg-info/requires.txt
ta_bitwarden_cli.egg-info/top_level.txt
ta_bitwarden_cli/binaries/bw-linux.zip
ta_bitwarden_cli/binaries/bw-macos.zip
ta_bitwarden_cli/binaries/bw-windows.zip
tests/test_download.py
tests/test_negative.py
tests/test_smoke.py