Metadata-Version: 2.1
Name: ta_bitwarden_cli
Version: 0.14.0
Summary: Thoughtful BitWarden CLI Package
Home-page: https://www.thoughtful.ai/
Author: Bohdan Sukhov
Author-email: bohdan.sukhov@thoughtfulautomation.com
Keywords: ta_bitwarden_cli
Classifier: Intended Audience :: Developers
Classifier: Natural Language :: English
Classifier: Programming Language :: Python :: 3
Classifier: Programming Language :: Python :: 3.8
Classifier: Programming Language :: Python :: 3.9
Requires-Python: >=3.8
Requires-Dist: retry~=0.9.2
Requires-Dist: requests<3.0.0,>=2.31.0
